adamix_gpt2/__init__.py
adamix_gpt2/data_utils.py
adamix_gpt2/encoder.py
adamix_gpt2/exp_utils.py
adamix_gpt2/expert_soup.py
adamix_gpt2/format_converting_dart.py
adamix_gpt2/format_converting_e2e.py
adamix_gpt2/format_converting_webnlg.py
adamix_gpt2/gpt2_beam.py
adamix_gpt2/gpt2_decode.py
adamix_gpt2/gpt2_encode.py
adamix_gpt2/gpt2_ft.py
adamix_gpt2/gpu.py
adamix_gpt2/model.py
adamix_gpt2/optimizer.py
adamix_gpt2/adamixlib/__init__.py
adamix_gpt2/adamixlib/layers.py
adamix_gpt2/adamixlib/utils.py
adamix_gpt2-0.0.2.dist-info/LICENSE
adamix_gpt2-0.0.2.dist-info/METADATA
adamix_gpt2-0.0.2.dist-info/WHEEL
adamix_gpt2-0.0.2.dist-info/dependency_links.txt
adamix_gpt2-0.0.2.dist-info/top_level.txt
adamix_gpt2-0.0.2.dist-info/RECORD
