Metadata-Version: 2.1
Name: adamix-gpt2
Version: 0.0.2
Summary: PyTorch implementation of low-rank adaptation (LoRA) and Adamix, a parameter-efficient approach to adapt a large pre-trained deep learning model which obtains performance better than full fine-tuning.
Home-page: https://github.com/microsoft/AdaMix
Author: Sahaj Agarwal
Author-email: sahagar@microsoft.com
Keywords: python,adamix,peft
Classifier: Programming Language :: Python :: 3
Classifier: License :: OSI Approved :: MIT License
Classifier: Operating System :: OS Independent
Requires-Python: >=3.6
License-File: LICENSE
Requires-Dist: transformers (==3.3.1)
Requires-Dist: spacy
Requires-Dist: tqdm
Requires-Dist: tensorboard
Requires-Dist: progress
Requires-Dist: loralib (==0.1.1)
